AUTHORS
ChangeLog
LICENSE
MANIFEST.in
README.md
setup.cfg
setup.py
docs/Makefile
docs/conf.py
docs/index.rst
docs/module_guide.rst
nextdl/__init__.py
nextdl/__main__.py
nextdl/aes.py
nextdl/cache.py
nextdl/compat.py
nextdl/jsinterp.py
nextdl/nextdl.py
nextdl/options.py
nextdl/socks.py
nextdl/swfinterp.py
nextdl/update.py
nextdl/utils.py
nextdl/version.py
nextdl.egg-info/PKG-INFO
nextdl.egg-info/SOURCES.txt
nextdl.egg-info/dependency_links.txt
nextdl.egg-info/entry_points.txt
nextdl.egg-info/top_level.txt
nextdl/downloader/__init__.py
nextdl/downloader/common.py
nextdl/downloader/dash.py
nextdl/downloader/external.py
nextdl/downloader/f4m.py
nextdl/downloader/fragment.py
nextdl/downloader/hls.py
nextdl/downloader/http.py
nextdl/downloader/ism.py
nextdl/downloader/rtmp.py
nextdl/downloader/rtsp.py
nextdl/extractor/__init__.py
nextdl/extractor/abc.py
nextdl/extractor/abcnews.py
nextdl/extractor/abcotvs.py
nextdl/extractor/academicearth.py
nextdl/extractor/acast.py
nextdl/extractor/adn.py
nextdl/extractor/adobeconnect.py
nextdl/extractor/adobepass.py
nextdl/extractor/adobetv.py
nextdl/extractor/adultswim.py
nextdl/extractor/aenetworks.py
nextdl/extractor/afreecatv.py
nextdl/extractor/airmozilla.py
nextdl/extractor/aliexpress.py
nextdl/extractor/aljazeera.py
nextdl/extractor/allocine.py
nextdl/extractor/alphaporno.py
nextdl/extractor/amara.py
nextdl/extractor/amcnetworks.py
nextdl/extractor/americastestkitchen.py
nextdl/extractor/amp.py
nextdl/extractor/animeondemand.py
nextdl/extractor/anvato.py
nextdl/extractor/aol.py
nextdl/extractor/apa.py
nextdl/extractor/aparat.py
nextdl/extractor/appleconnect.py
nextdl/extractor/applepodcasts.py
nextdl/extractor/appletrailers.py
nextdl/extractor/archiveorg.py
nextdl/extractor/arcpublishing.py
nextdl/extractor/ard.py
nextdl/extractor/arkena.py
nextdl/extractor/arnes.py
nextdl/extractor/arte.py
nextdl/extractor/asiancrush.py
nextdl/extractor/atresplayer.py
nextdl/extractor/atttechchannel.py
nextdl/extractor/atvat.py
nextdl/extractor/audimedia.py
nextdl/extractor/audioboom.py
nextdl/extractor/audiomack.py
nextdl/extractor/awaan.py
nextdl/extractor/aws.py
nextdl/extractor/azmedien.py
